Cupboard-0.2.3.dist-info/DESCRIPTION.rst
Cupboard-0.2.3.dist-info/METADATA
Cupboard-0.2.3.dist-info/RECORD
Cupboard-0.2.3.dist-info/WHEEL
Cupboard-0.2.3.dist-info/metadata.json
Cupboard-0.2.3.dist-info/top_level.txt
cupboard/__init__.py
cupboard/backend.py
cupboard/marshal.py
cupboard/store.py
